gtkspellcheck/__init__.py
gtkspellcheck/_oxt_extract.py
gtkspellcheck/_pylocales/__init__.py
gtkspellcheck/_pylocales/locales.db
gtkspellcheck/_pylocales/locales.py
gtkspellcheck/spellcheck.py
pygtkspellcheck-5.0.2.dist-info/LICENSE
pygtkspellcheck-5.0.2.dist-info/METADATA
pygtkspellcheck-5.0.2.dist-info/WHEEL
pygtkspellcheck-5.0.2.dist-info/RECORD
