Metadata-Version: 2.1
Name: pygtkspellcheck
Version: 5.0.2
Summary: A simple but quite powerful spellchecking library for GTK written in pure Python.
Home-page: https://github.com/koehlma/pygtkspellcheck
License: GPL-3.0-or-later
Author: Maximilian Köhl
Author-email: mail@koehlma.de
Requires-Python: >=3.7,<4.0
Classifier: Development Status :: 5 - Production/Stable
Classifier: Environment :: X11 Applications :: GTK
Classifier: Environment :: X11 Applications :: Gnome
Classifier: Intended Audience :: Developers
Classifier: License :: OSI Approved :: GNU General Public License v3 or later (GPLv3+)
Classifier: Operating System :: MacOS
Classifier: Operating System :: Microsoft :: Windows
Classifier: Operating System :: POSIX
Classifier: Programming Language :: Python :: 3
Classifier: Programming Language :: Python :: 3.7
Classifier: Programming Language :: Python :: 3.8
Classifier: Programming Language :: Python :: 3.9
Classifier: Programming Language :: Python :: 3.10
Classifier: Programming Language :: Python :: 3.11
Classifier: Programming Language :: Python :: 3
Classifier: Topic :: Software Development :: Localization
Provides-Extra: docs
Requires-Dist: PyGObject (>=3.42.1,<4.0.0)
Requires-Dist: myst-parser (>=0.18.0,<0.19.0) ; extra == "docs"
Requires-Dist: pyenchant (>=3.0,<4.0)
Requires-Dist: sphinx (>=4.5.0,<5.0.0) ; extra == "docs"
Project-URL: Repository, https://github.com/koehlma/pygtkspellcheck.git
